nearust/__init__.py
nearust/_lib.cp311-win32.pyd
nearust/_symdel.py
nearust-0.4.0.dist-info/licenses/LICENSE.txt
nearust-0.4.0.dist-info/METADATA
nearust-0.4.0.dist-info/WHEEL
nearust-0.4.0.dist-info/top_level.txt
nearust-0.4.0.dist-info/RECORD
